README.md
setup.py
catalogos_cp_mex.egg-info/PKG-INFO
catalogos_cp_mex.egg-info/SOURCES.txt
catalogos_cp_mex.egg-info/dependency_links.txt
catalogos_cp_mex.egg-info/requires.txt
catalogos_cp_mex.egg-info/top_level.txt
management/__init__.py
management/commands/__init__.py
management/commands/load_catalogs.py
migrations/0001_initial.py
migrations/__init__.py