Metadata-Version: 2.1
Name: catalogos-cp-mex
Version: 0.0.3
Summary: Permite migrar los codigos postales de México
Home-page: UNKNOWN
License: UNKNOWN
Platform: UNKNOWN
